mavprint/mavprint.py
mavprint-0.1.dist-info/LICENSE
mavprint-0.1.dist-info/METADATA
mavprint-0.1.dist-info/WHEEL
mavprint-0.1.dist-info/entry_points.txt
mavprint-0.1.dist-info/top_level.txt
mavprint-0.1.dist-info/RECORD
