Metadata-Version: 2.1
Name: mavprint
Version: 0.1
Summary: print mavlink messages to console
Home-page: https://github.com/evidlo/mavprint
Author: Evan Widloski
Author-email: evan@evanw.org
License: GPLv3
Keywords: mavlink debug ardupilot
Platform: UNKNOWN
Classifier: Programming Language :: Python :: 3
Requires-Dist: pymavlink
